pydog/__init__.py
pydog/const.py
pydog/pydog.py
pydog-0.1.0.dist-info/METADATA
pydog-0.1.0.dist-info/WHEEL
pydog-0.1.0.dist-info/top_level.txt
pydog-0.1.0.dist-info/RECORD
