Metadata-Version: 2.1
Name: pydog
Version: 0.1.0
Summary: A Simple Python API Wrapper for https://dog.ceo.
Home-page: UNKNOWN
Author: Daniel Ahn
Author-email: firefwing42@gmail.com
License: UNKNOWN
Platform: UNKNOWN
Requires-Dist: requests
